gdsr-0.1.0.dist-info/METADATA
gdsr-0.1.0.dist-info/WHEEL
gdsr-0.1.0.dist-info/license_files/LICENSE
gdsr/_gdsr.pyi
gdsr/py.typed
gdsr/typings/__init__.py
gdsr/__init__.py
gdsr/logging/__init__.py
gdsr/logging/setup.py
gdsr/_gdsr.pypy310-pp73-aarch64-linux-gnu.so
gdsr-0.1.0.dist-info/RECORD
