Metadata-Version: 2.3
Name: gdsr
Version: 0.1.0
Classifier: Programming Language :: Rust
Classifier: Programming Language :: Python :: Implementation :: PyPy
Requires-Dist: typing-extensions ; python_version < '3.11'
Requires-Dist: maturin ; extra == 'dev'
Requires-Dist: ruff ; extra == 'dev'
Requires-Dist: mypy ; extra == 'dev'
Requires-Dist: isort ; extra == 'dev'
Requires-Dist: pytest ; extra == 'dev'
Requires-Dist: hypothesis ; extra == 'dev'
Requires-Dist: pytest-randomly ; extra == 'dev'
Requires-Dist: pytest-xdist ; extra == 'dev'
Requires-Dist: mkdocs ; extra == 'docs'
Requires-Dist: mkdocstrings-python ; extra == 'docs'
Requires-Dist: mkdocs-material ; extra == 'docs'
Requires-Dist: pytest ; extra == 'test'
Requires-Dist: hypothesis ; extra == 'test'
Requires-Dist: pytest-randomly ; extra == 'test'
Requires-Dist: pytest-xdist ; extra == 'test'
Requires-Dist: ruff ; extra == 'lint'
Requires-Dist: mypy ; extra == 'lint'
Requires-Dist: isort ; extra == 'lint'
Provides-Extra: dev
Provides-Extra: docs
Provides-Extra: test
Provides-Extra: lint
License-File: LICENSE
Keywords: gdsr,rust,python,pyo3,GDSII,CAD
Author-email: Matthew Mckee <matthewmckee04@yahoo.co.uk>
Requires-Python: >=3.10
Project-URL: Documentation, https://MatthewMckee4.github.io/gdsr/
Project-URL: Repository, https://github.com/MatthewMckee4/gdsr
Project-URL: Issues, https://github.com/MatthewMckee4/gdsr/issues
